{
  "$schema": "https://raw.githubusercontent.com/spdx/spdx-spec/v2.2.1/schemas/spdx-schema.json",
  "spdxVersion": "SPDX-2.2",
  "dataLicense": "CC0-1.0",
  "SPDXID": "SPDXRef-DOCUMENT",
  "documentNamespace": "https://spdx.org/spdxdocs/meshoptimizer-x64-windows-0.21-f76f0193-e23b-46b6-a55a-96395fc0c648",
  "name": "meshoptimizer:x64-windows@0.21 95f6a0f315e50f850f9b8ad6ea870836084a14a8673a4502d2696db94257f638",
  "creationInfo": {
    "creators": [
      "Tool: vcpkg-2024-08-01-fd884a0d390d12783076341bd43d77c3a6a15658"
    ],
    "created": "2025-02-01T01:55:23Z"
  },
  "relationships": [
    {
      "spdxElementId": "SPDXRef-port",
      "relationshipType": "GENERATES",
      "relatedSpdxElement": "SPDXRef-binary"
    },
    {
      "spdxElementId": "SPDXRef-port",
      "relationshipType": "CONTAINS",
      "relatedSpdxElement": "SPDXRef-file-0"
    },
    {
      "spdxElementId": "SPDXRef-port",
      "relationshipType": "CONTAINS",
      "relatedSpdxElement": "SPDXRef-file-1"
    },
    {
      "spdxElementId": "SPDXRef-binary",
      "relationshipType": "GENERATED_FROM",
      "relatedSpdxElement": "SPDXRef-port"
    },
    {
      "spdxElementId": "SPDXRef-file-0",
      "relationshipType": "CONTAINED_BY",
      "relatedSpdxElement": "SPDXRef-port"
    },
    {
      "spdxElementId": "SPDXRef-file-1",
      "relationshipType": "CONTAINED_BY",
      "relatedSpdxElement": "SPDXRef-port"
    }
  ],
  "packages": [
    {
      "name": "meshoptimizer",
      "SPDXID": "SPDXRef-port",
      "versionInfo": "0.21",
      "downloadLocation": "git+https://github.com/microsoft/vcpkg@9ff504432cfa14706fac154ca9c490a3df9922f8",
      "homepage": "https://github.com/zeux/meshoptimizer",
      "licenseConcluded": "MIT",
      "licenseDeclared": "NOASSERTION",
      "copyrightText": "NOASSERTION",
      "description": "Mesh optimization library that makes meshes smaller and faster to render",
      "comment": "This is the port (recipe) consumed by vcpkg."
    },
    {
      "name": "meshoptimizer:x64-windows",
      "SPDXID": "SPDXRef-binary",
      "versionInfo": "95f6a0f315e50f850f9b8ad6ea870836084a14a8673a4502d2696db94257f638",
      "downloadLocation": "NONE",
      "licenseConcluded": "MIT",
      "licenseDeclared": "NOASSERTION",
      "copyrightText": "NOASSERTION",
      "comment": "This is a binary package built by vcpkg."
    },
    {
      "SPDXID": "SPDXRef-resource-1",
      "name": "zeux/meshoptimizer",
      "downloadLocation": "git+https://github.com/zeux/meshoptimizer@v0.21",
      "licenseConcluded": "NOASSERTION",
      "licenseDeclared": "NOASSERTION",
      "copyrightText": "NOASSERTION",
      "checksums": [
        {
          "algorithm": "SHA512",
          "checksumValue": "801cdc911da6ece7afe2ae4f5d002f27e8a0b5072ec4332968183941671024b3cda2a45266c0899cc9fb134d3b931d70b3bd9629dc7765f77e102146b2f6bfd0"
        }
      ]
    }
  ],
  "files": [
    {
      "fileName": "./C:/Users/farhan/AppData/Local/vcpkg/registries/git-trees/9ff504432cfa14706fac154ca9c490a3df9922f8/portfile.cmake",
      "SPDXID": "SPDXRef-file-0",
      "checksums": [
        {
          "algorithm": "SHA256",
          "checksumValue": "7b4db7a587d22abe08501daf17144a33e539e16127e76d340e0fe61dee8c33a9"
        }
      ],
      "licenseConcluded": "NOASSERTION",
      "copyrightText": "NOASSERTION"
    },
    {
      "fileName": "./C:/Users/farhan/AppData/Local/vcpkg/registries/git-trees/9ff504432cfa14706fac154ca9c490a3df9922f8/vcpkg.json",
      "SPDXID": "SPDXRef-file-1",
      "checksums": [
        {
          "algorithm": "SHA256",
          "checksumValue": "fa42a4852bb5356bb4fd960a8809ba19c2124c05268b6276f0ea28ba7c6bbfd9"
        }
      ],
      "licenseConcluded": "NOASSERTION",
      "copyrightText": "NOASSERTION"
    }
  ]
}
